remoteprotocols/__init__.py
remoteprotocols/__main__.py
remoteprotocols/protocol.py
remoteprotocols/py.typed
remoteprotocols/registry.py
remoteprotocols/validators.py
remoteprotocols/codecs/__init__.py
remoteprotocols/codecs/decoder.py
remoteprotocols/codecs/encoder.py
remoteprotocols/codecs/pattern.py
remoteprotocols/codecs/protocols.yaml
remoteprotocols/codecs/protocols_raw.yaml
remoteprotocols/codecs/schema1.py
remoteprotocols/codecs/schema2.py
remoteprotocols/raw/__init__.py
remoteprotocols/raw/broadlink.py
remoteprotocols/raw/duration.py
remoteprotocols/raw/miio.py
remoteprotocols/raw/pronto.py
remoteprotocols-0.0.7.dist-info/METADATA
remoteprotocols-0.0.7.dist-info/WHEEL
remoteprotocols-0.0.7.dist-info/entry_points.txt
remoteprotocols-0.0.7.dist-info/top_level.txt
remoteprotocols-0.0.7.dist-info/RECORD
