Metadata-Version: 2.1
Name: remoteprotocols
Version: 0.0.7
Summary: Manage and convert many IR / RF remote protocols
Home-page: https://github.com/ianchi/remoteprotocols
Author: Adrian Panella
Author-email: ianchi74@outlook.com
License: MIT
Project-URL: Bug Tracker, https://github.com/ianchi/remoteprotocols/issues
Platform: UNKNOWN
Classifier: Programming Language :: Python :: 3
Classifier: License :: OSI Approved :: MIT License
Classifier: Operating System :: OS Independent
Classifier: Topic :: Software Development :: Embedded Systems
Classifier: Topic :: Home Automation
Requires-Python: >=3.8
Requires-Dist: voluptuous (<1.0,>=0.12.2)
